gibby/__init__.py
gibby/__main__.py
gibby/errors.py
gibby/file_tree.py
gibby/git.py
gibby/logic.py
gibby/snapshot_behavior.py
gibby/cli/__init__.py
gibby/cli/__main__.py
gibby/cli/_utils.py
gibby/cli/snapshot.py
gibby/remote_url/__init__.py
gibby/remote_url/file_remote_url.py
gibby/remote_url/remote_url.py
gibby-3.1.1.dist-info/LICENSE.txt
gibby-3.1.1.dist-info/METADATA
gibby-3.1.1.dist-info/WHEEL
gibby-3.1.1.dist-info/entry_points.txt
gibby-3.1.1.dist-info/top_level.txt
gibby-3.1.1.dist-info/RECORD
